tbcm/__init__.py
tbcm/tb_inferno.py
tbcm/tb_oleron.py
tbcm/tb_sunrise.py
tbcm-0.5.dist-info/LICENSE
tbcm-0.5.dist-info/METADATA
tbcm-0.5.dist-info/WHEEL
tbcm-0.5.dist-info/top_level.txt
tbcm-0.5.dist-info/RECORD
