Metadata-Version: 2.2
Name: tbcm
Version: 0.5
Summary: Ten Bit Color Maps
Home-page: https://github.com/artiedins/tbcm
Author: Artie Dins
License: MIT
License-File: LICENSE
Requires-Dist: matplotlib
Dynamic: author
Dynamic: description
Dynamic: description-content-type
Dynamic: home-page
Dynamic: license
Dynamic: requires-dist
Dynamic: summary
